unichunking/__init__.py
unichunking/formating/__init__.py
unichunking/formating/chunking.py
unichunking/formating/pages.py
unichunking/formating/subchunking.py
unichunking/formating/utils.py
unichunking/settings/__init__.py
unichunking/settings/chunking.py
unichunking/settings/files.py
unichunking/settings/text.py
unichunking/settings/unisettings.py
unichunking/subchunk_extraction/__init__.py
unichunking/subchunk_extraction/docx_sub_chunking.py
unichunking/subchunk_extraction/ipynb_sub_chunking.py
unichunking/subchunk_extraction/pdf_sub_chunking.py
unichunking/subchunk_extraction/pptx_sub_chunking.py
unichunking/subchunk_extraction/txt_sub_chunking.py
unichunking/subchunk_extraction/xlsx_sub_chunking.py
unichunking/subchunk_extraction/xlsx_utils.py
unichunking/tools/__init__.py
unichunking/tools/chunk_cleaning.py
unichunking/tools/file_converter.py
unichunking/tools/markdown_interpreter.py
unichunking/tools/table_processing.py
unichunking/tools/xml_tools.py
unichunking/types/__init__.py
unichunking/types/chunking.py
unichunking/types/matrix_table.py
unichunking/types/status.py
unichunking/types/subchunking.py
unichunking/utils/__init__.py
unichunking/utils/file_converter.py
unichunking/utils/logger.py
unichunking/utils/profiler.py
delos_unichunking-1.2.0.dist-info/LICENSE
delos_unichunking-1.2.0.dist-info/METADATA
delos_unichunking-1.2.0.dist-info/WHEEL
delos_unichunking-1.2.0.dist-info/RECORD
